setup.py
gb_krkk_distributions/Binomialdistribution.py
gb_krkk_distributions/Gaussiandistribution.py
gb_krkk_distributions/Generaldistribution.py
gb_krkk_distributions/__init__.py
gb_krkk_distributions.egg-info/PKG-INFO
gb_krkk_distributions.egg-info/SOURCES.txt
gb_krkk_distributions.egg-info/dependency_links.txt
gb_krkk_distributions.egg-info/not-zip-safe
gb_krkk_distributions.egg-info/top_level.txt