Metadata-Version: 1.0
Name: gb-krkk-distributions
Version: 1.2
Summary: Gaussian and binomial distributions
Home-page: UNKNOWN
Author: Rushi
Author-email: rushikirankuchipudi@gmail.com
License: UNKNOWN
Platform: UNKNOWN
